demos/__init__.py
sql_scripts/__init__.py
sql_scripts/test.py
sql_scripts-1.0.dist-info/LICENSE
sql_scripts-1.0.dist-info/METADATA
sql_scripts-1.0.dist-info/WHEEL
sql_scripts-1.0.dist-info/top_level.txt
sql_scripts-1.0.dist-info/RECORD
