Metadata-Version: 2.1
Name: sql-scripts
Version: 1.0
Summary: 脚本规范
Home-page: UNKNOWN
Author: lipanpan
Author-email: 1299793997@qq.com
License: UNKNOWN
Platform: UNKNOWN
Classifier: Programming Language :: Python :: 3
Classifier: License :: OSI Approved :: MIT License
Classifier: Operating System :: OS Independent
Requires-Python: >=3
License-File: LICENSE
Requires-Dist: PyMySQL
